[{"imageLink":"https://images.olx.com.pk/thumbnails/224533502-240x180.jpeg"},{"imageLink":"https://images.olx.com.pk/thumbnails/226260856-240x180.jpeg"},{"imageLink":"https://images.olx.com.pk/thumbnails/223444290-240x180.jpeg"},{"imageLink":"https://images.olx.com.pk/thumbnails/225658670-240x180.jpeg"},{"imageLink":"https://images.olx.com.pk/thumbnails/226993686-240x180.jpeg"},{"imageLink":"https://images.olx.com.pk/thumbnails/227286651-240x180.jpeg"},{"imageLink":"https://images.olx.com.pk/thumbnails/228719027-240x180.jpeg"},{"imageLink":"https://images.olx.com.pk/thumbnails/228718906-240x180.jpeg"},{"imageLink":"https://images.olx.com.pk/thumbnails/228718724-240x180.jpeg"},{"imageLink":"https://images.olx.com.pk/thumbnails/228718708-240x180.jpeg"},{"imageLink":"https://images.olx.com.pk/thumbnails/228718639-240x180.jpeg"},{"imageLink":"https://images.olx.com.pk/thumbnails/228719006-240x180.jpeg"},{"imageLink":"https://images.olx.com.pk/thumbnails/228718546-240x180.jpeg"},{"imageLink":"https://images.olx.com.pk/thumbnails/228718506-240x180.jpeg"},{"imageLink":"https://images.olx.com.pk/thumbnails/228718456-240x180.jpeg"},{"imageLink":"https://images.olx.com.pk/thumbnails/228718397-240x180.jpeg"},{"imageLink":"https://images.olx.com.pk/thumbnails/228718221-240x180.jpeg"},{"imageLink":"https://images.olx.com.pk/thumbnails/228718193-240x180.jpeg"},{"imageLink":"https://images.olx.com.pk/thumbnails/228718185-240x180.jpeg"},{"imageLink":"https://images.olx.com.pk/thumbnails/228718149-240x180.jpeg"},{"imageLink":"https://images.olx.com.pk/thumbnails/226304553-240x180.jpeg"},{"imageLink":"https://images.olx.com.pk/thumbnails/228099241-240x180.jpeg"},{"imageLink":"https://images.olx.com.pk/thumbnails/227419362-240x180.jpeg"},{"imageLink":"https://images.olx.com.pk/thumbnails/227803445-240x180.jpeg"},{"imageLink":"https://images.olx.com.pk/thumbnails/226726716-240x180.jpeg"},{"imageLink":"https://images.olx.com.pk/thumbnails/227725072-240x180.jpeg"},{"imageLink":"https://images.olx.com.pk/thumbnails/228718185-240x180.jpeg"},{"imageLink":"https://images.olx.com.pk/thumbnails/228718149-240x180.jpeg"},{"imageLink":"https://images.olx.com.pk/thumbnails/219086152-240x180.jpeg"},{"imageLink":"https://images.olx.com.pk/thumbnails/228718086-240x180.jpeg"},{"imageLink":"https://images.olx.com.pk/thumbnails/228718069-240x180.jpeg"},{"imageLink":"https://images.olx.com.pk/thumbnails/228717968-240x180.jpeg"},{"imageLink":"https://images.olx.com.pk/thumbnails/228717727-240x180.jpeg"},{"imageLink":"https://images.olx.com.pk/thumbnails/228717698-240x180.jpeg"},{"imageLink":"https://images.olx.com.pk/thumbnails/228717635-240x180.jpeg"},{"imageLink":"https://images.olx.com.pk/thumbnails/226915299-240x180.jpeg"},{"imageLink":"https://images.olx.com.pk/thumbnails/220317666-240x180.jpeg"},{"imageLink":"https://images.olx.com.pk/thumbnails/228717495-240x180.jpeg"},{"imageLink":"https://images.olx.com.pk/thumbnails/228717393-240x180.jpeg"},{"imageLink":"https://images.olx.com.pk/thumbnails/228717352-240x180.jpeg"},{"imageLink":"https://images.olx.com.pk/thumbnails/225741094-240x180.jpeg"},{"imageLink":"https://images.olx.com.pk/thumbnails/221685824-240x180.jpeg"},{"imageLink":"https://images.olx.com.pk/thumbnails/226587785-240x180.jpeg"},{"imageLink":"https://images.olx.com.pk/thumbnails/223791497-240x180.jpeg"},{"imageLink":"https://images.olx.com.pk/thumbnails/226802375-240x180.jpeg"},{"imageLink":"https://images.olx.com.pk/thumbnails/228299438-240x180.jpeg"},{"imageLink":"https://images.olx.com.pk/thumbnails/228717293-240x180.jpeg"},{"imageLink":"https://images.olx.com.pk/thumbnails/228717177-240x180.jpeg"},{"imageLink":"https://images.olx.com.pk/thumbnails/228717120-240x180.jpeg"},{"imageLink":"https://images.olx.com.pk/thumbnails/228717064-240x180.jpeg"},{"imageLink":"https://images.olx.com.pk/thumbnails/228716954-240x180.jpeg"},{"imageLink":"https://images.olx.com.pk/thumbnails/228716935-240x180.jpeg"},{"imageLink":"https://images.olx.com.pk/thumbnails/193585894-240x180.jpeg"},{"imageLink":"https://images.olx.com.pk/thumbnails/228716889-240x180.jpeg"},{"imageLink":"https://images.olx.com.pk/thumbnails/228716841-240x180.jpeg"},{"imageLink":"https://images.olx.com.pk/thumbnails/228716742-240x180.jpeg"},{"imageLink":"https://images.olx.com.pk/thumbnails/228716658-240x180.jpeg"},{"imageLink":"https://images.olx.com.pk/thumbnails/228716640-240x180.jpeg"},{"imageLink":"https://images.olx.com.pk/thumbnails/228716592-240x180.jpeg"},{"imageLink":"https://images.olx.com.pk/thumbnails/228716585-240x180.jpeg"},{"imageLink":"https://images.olx.com.pk/thumbnails/228533517-240x180.jpeg"},{"imageLink":"https://images.olx.com.pk/thumbnails/226960649-240x180.jpeg"},{"imageLink":"https://images.olx.com.pk/thumbnails/227322832-240x180.jpeg"},{"imageLink":"https://images.olx.com.pk/thumbnails/227885087-240x180.jpeg"},{"imageLink":"https://images.olx.com.pk/thumbnails/225303123-240x180.jpeg"},{"imageLink":"https://images.olx.com.pk/thumbnails/203518510-240x180.jpeg"},{"imageLink":"https://images.olx.com.pk/thumbnails/228716585-240x180.jpeg"},{"imageLink":"https://images.olx.com.pk/thumbnails/228716542-240x180.jpeg"},{"imageLink":"https://images.olx.com.pk/thumbnails/228716432-240x180.jpeg"},{"imageLink":"https://images.olx.com.pk/thumbnails/226882159-240x180.jpeg"},{"imageLink":"https://images.olx.com.pk/thumbnails/216370598-240x180.jpeg"},{"imageLink":"https://images.olx.com.pk/thumbnails/228716261-240x180.jpeg"},{"imageLink":"https://images.olx.com.pk/thumbnails/228716249-240x180.jpeg"},{"imageLink":"https://images.olx.com.pk/thumbnails/228716192-240x180.jpeg"},{"imageLink":"https://images.olx.com.pk/thumbnails/228716182-240x180.jpeg"},{"imageLink":"https://images.olx.com.pk/thumbnails/228716133-240x180.jpeg"},{"imageLink":"https://images.olx.com.pk/thumbnails/228715998-240x180.jpeg"},{"imageLink":"https://images.olx.com.pk/thumbnails/228715958-240x180.jpeg"},{"imageLink":"https://images.olx.com.pk/thumbnails/228715939-240x180.jpeg"},{"imageLink":"https://images.olx.com.pk/thumbnails/228715872-240x180.jpeg"},{"imageLink":"https://images.olx.com.pk/thumbnails/227128793-240x180.jpeg"},{"imageLink":"https://images.olx.com.pk/thumbnails/221942740-240x180.jpeg"},{"imageLink":"https://images.olx.com.pk/thumbnails/227507863-240x180.jpeg"},{"imageLink":"https://images.olx.com.pk/thumbnails/223083282-240x180.jpeg"},{"imageLink":"https://images.olx.com.pk/thumbnails/227961221-240x180.jpeg"},{"imageLink":"https://images.olx.com.pk/thumbnails/225739303-240x180.jpeg"},{"imageLink":"https://images.olx.com.pk/thumbnails/228715831-240x180.jpeg"},{"imageLink":"https://images.olx.com.pk/thumbnails/228715802-240x180.jpeg"},{"imageLink":"https://images.olx.com.pk/thumbnails/228715799-240x180.jpeg"},{"imageLink":"https://images.olx.com.pk/thumbnails/228715761-240x180.jpeg"},{"imageLink":"https://images.olx.com.pk/thumbnails/228715745-240x180.jpeg"},{"imageLink":"https://images.olx.com.pk/thumbnails/228714933-240x180.jpeg"},{"imageLink":"https://images.olx.com.pk/thumbnails/228715910-240x180.jpeg"},{"imageLink":"https://images.olx.com.pk/thumbnails/228715692-240x180.jpeg"},{"imageLink":"https://images.olx.com.pk/thumbnails/228715531-240x180.jpeg"},{"imageLink":"https://images.olx.com.pk/thumbnails/228715504-240x180.jpeg"},{"imageLink":"https://images.olx.com.pk/thumbnails/228715262-240x180.jpeg"},{"imageLink":"https://images.olx.com.pk/thumbnails/228715191-240x180.jpeg"},{"imageLink":"https://images.olx.com.pk/thumbnails/228715134-240x180.jpeg"},{"imageLink":"https://images.olx.com.pk/thumbnails/228715087-240x180.jpeg"},{"imageLink":"https://images.olx.com.pk/thumbnails/223445299-240x180.jpeg"},{"imageLink":"https://images.olx.com.pk/thumbnails/220898120-240x180.jpeg"},{"imageLink":"https://images.olx.com.pk/thumbnails/227655443-240x180.jpeg"},{"imageLink":"https://images.olx.com.pk/thumbnails/172561283-240x180.jpeg"},{"imageLink":"https://images.olx.com.pk/thumbnails/225976378-240x180.jpeg"},{"imageLink":"https://images.olx.com.pk/thumbnails/226497169-240x180.jpeg"},{"imageLink":"https://images.olx.com.pk/thumbnails/210118225-240x180.jpeg"},{"imageLink":"https://images.olx.com.pk/thumbnails/209764354-240x180.jpeg"},{"imageLink":"https://images.olx.com.pk/thumbnails/228714964-240x180.jpeg"},{"imageLink":"https://images.olx.com.pk/thumbnails/228714900-240x180.jpeg"},{"imageLink":"https://images.olx.com.pk/thumbnails/228714856-240x180.jpeg"},{"imageLink":"https://images.olx.com.pk/thumbnails/228714777-240x180.jpeg"},{"imageLink":"https://images.olx.com.pk/thumbnails/228714663-240x180.jpeg"},{"imageLink":"https://images.olx.com.pk/thumbnails/228714637-240x180.jpeg"},{"imageLink":"https://images.olx.com.pk/thumbnails/228714581-240x180.jpeg"},{"imageLink":"https://images.olx.com.pk/thumbnails/228714543-240x180.jpeg"},{"imageLink":"https://images.olx.com.pk/thumbnails/228714469-240x180.jpeg"},{"imageLink":"https://images.olx.com.pk/thumbnails/228714461-240x180.jpeg"},{"imageLink":"https://images.olx.com.pk/thumbnails/226713080-240x180.jpeg"},{"imageLink":"https://images.olx.com.pk/thumbnails/221200758-240x180.jpeg"},{"imageLink":"https://images.olx.com.pk/thumbnails/226032569-240x180.jpeg"},{"imageLink":"https://images.olx.com.pk/thumbnails/228225176-240x180.jpeg"},{"imageLink":"https://images.olx.com.pk/thumbnails/227599157-240x180.jpeg"},{"imageLink":"https://images.olx.com.pk/thumbnails/222775126-240x180.jpeg"},{"imageLink":"https://images.olx.com.pk/thumbnails/226140231-240x180.jpeg"},{"imageLink":"https://images.olx.com.pk/thumbnails/227419362-240x180.jpeg"},{"imageLink":"https://images.olx.com.pk/thumbnails/217862418-240x180.jpeg"},{"imageLink":"https://images.olx.com.pk/thumbnails/215559747-240x180.jpeg"},{"imageLink":"https://images.olx.com.pk/thumbnails/208874771-240x180.jpeg"},{"imageLink":"https://images.olx.com.pk/thumbnails/202998418-240x180.jpeg"},{"imageLink":"https://images.olx.com.pk/thumbnails/201449801-240x180.jpeg"},{"imageLink":"https://images.olx.com.pk/thumbnails/228714135-240x180.jpeg"},{"imageLink":"https://images.olx.com.pk/thumbnails/228713651-240x180.jpeg"},{"imageLink":"https://images.olx.com.pk/thumbnails/228713600-240x180.jpeg"},{"imageLink":"https://images.olx.com.pk/thumbnails/228713563-240x180.jpeg"},{"imageLink":"https://images.olx.com.pk/thumbnails/228713510-240x180.jpeg"},{"imageLink":"https://images.olx.com.pk/thumbnails/228713491-240x180.jpeg"},{"imageLink":"https://images.olx.com.pk/thumbnails/228713476-240x180.jpeg"},{"imageLink":"https://images.olx.com.pk/thumbnails/228713445-240x180.jpeg"},{"imageLink":"https://images.olx.com.pk/thumbnails/228713924-240x180.jpeg"},{"imageLink":"https://images.olx.com.pk/thumbnails/228641210-240x180.jpeg"},{"imageLink":"https://images.olx.com.pk/thumbnails/226969042-240x180.jpeg"},{"imageLink":"https://images.olx.com.pk/thumbnails/219207613-240x180.jpeg"},{"imageLink":"https://images.olx.com.pk/thumbnails/227869998-240x180.jpeg"},{"imageLink":"https://images.olx.com.pk/thumbnails/228113020-240x180.jpeg"},{"imageLink":"https://images.olx.com.pk/thumbnails/226123439-240x180.jpeg"},{"imageLink":"https://images.olx.com.pk/thumbnails/226498057-240x180.jpeg"},{"imageLink":"https://images.olx.com.pk/thumbnails/219521315-240x180.jpeg"},{"imageLink":"https://images.olx.com.pk/thumbnails/228713375-240x180.jpeg"},{"imageLink":"https://images.olx.com.pk/thumbnails/228713264-240x180.jpeg"},{"imageLink":"https://images.olx.com.pk/thumbnails/228715040-240x180.jpeg"},{"imageLink":"https://images.olx.com.pk/thumbnails/228713209-240x180.jpeg"},{"imageLink":"https://images.olx.com.pk/thumbnails/228713198-240x180.jpeg"},{"imageLink":"https://images.olx.com.pk/thumbnails/228713015-240x180.jpeg"},{"imageLink":"https://images.olx.com.pk/thumbnails/228712969-240x180.jpeg"},{"imageLink":"https://images.olx.com.pk/thumbnails/228712886-240x180.jpeg"},{"imageLink":"https://images.olx.com.pk/thumbnails/228712865-240x180.jpeg"},{"imageLink":"https://images.olx.com.pk/thumbnails/228712598-240x180.jpeg"},{"imageLink":"https://images.olx.com.pk/thumbnails/223103494-240x180.jpeg"},{"imageLink":"https://images.olx.com.pk/thumbnails/164478409-240x180.jpeg"},{"imageLink":"https://images.olx.com.pk/thumbnails/228300711-240x180.jpeg"},{"imageLink":"https://images.olx.com.pk/thumbnails/218542302-240x180.jpeg"},{"imageLink":"https://images.olx.com.pk/thumbnails/226185124-240x180.jpeg"},{"imageLink":"https://images.olx.com.pk/thumbnails/223227001-240x180.jpeg"},{"imageLink":"https://images.olx.com.pk/thumbnails/212459308-240x180.jpeg"},{"imageLink":"https://images.olx.com.pk/thumbnails/226095240-240x180.jpeg"},{"imageLink":"https://images.olx.com.pk/thumbnails/223103494-240x180.jpeg"},{"imageLink":"https://images.olx.com.pk/thumbnails/164478409-240x180.jpeg"},{"imageLink":"https://images.olx.com.pk/thumbnails/228712816-240x180.jpeg"},{"imageLink":"https://images.olx.com.pk/thumbnails/228712622-240x180.jpeg"},{"imageLink":"https://images.olx.com.pk/thumbnails/228712572-240x180.jpeg"},{"imageLink":"https://images.olx.com.pk/thumbnails/228712518-240x180.jpeg"},{"imageLink":"https://images.olx.com.pk/thumbnails/228712477-240x180.jpeg"},{"imageLink":"https://images.olx.com.pk/thumbnails/228712439-240x180.jpeg"},{"imageLink":"https://images.olx.com.pk/thumbnails/228712433-240x180.jpeg"},{"imageLink":"https://images.olx.com.pk/thumbnails/228712371-240x180.jpeg"},{"imageLink":"https://images.olx.com.pk/thumbnails/228712362-240x180.jpeg"},{"imageLink":"https://images.olx.com.pk/thumbnails/228712349-240x180.jpeg"},{"imageLink":"https://images.olx.com.pk/thumbnails/228712302-240x180.jpeg"},{"imageLink":"https://images.olx.com.pk/thumbnails/228713394-240x180.jpeg"},{"imageLink":"https://images.olx.com.pk/thumbnails/227022427-240x180.jpeg"},{"imageLink":"https://images.olx.com.pk/thumbnails/228141926-240x180.jpeg"},{"imageLink":"https://images.olx.com.pk/thumbnails/226497026-240x180.jpeg"},{"imageLink":"https://images.olx.com.pk/thumbnails/224907074-240x180.jpeg"},{"imageLink":"https://images.olx.com.pk/thumbnails/227705353-240x180.jpeg"},{"imageLink":"https://images.olx.com.pk/thumbnails/227876263-240x180.jpeg"},{"imageLink":"https://images.olx.com.pk/thumbnails/228712235-240x180.jpeg"},{"imageLink":"https://images.olx.com.pk/thumbnails/220784148-240x180.jpeg"},{"imageLink":"https://images.olx.com.pk/thumbnails/228712167-240x180.jpeg"},{"imageLink":"https://images.olx.com.pk/thumbnails/228712125-240x180.jpeg"},{"imageLink":"https://images.olx.com.pk/thumbnails/228712063-240x180.jpeg"},{"imageLink":"https://images.olx.com.pk/thumbnails/228712030-240x180.jpeg"},{"imageLink":"https://images.olx.com.pk/thumbnails/228711994-240x180.jpeg"},{"imageLink":"https://images.olx.com.pk/thumbnails/228711968-240x180.jpeg"},{"imageLink":"https://images.olx.com.pk/thumbnails/228711807-240x180.jpeg"},{"imageLink":"https://images.olx.com.pk/thumbnails/228711791-240x180.jpeg"},{"imageLink":"https://images.olx.com.pk/thumbnails/228711761-240x180.jpeg"},{"imageLink":"https://images.olx.com.pk/thumbnails/228711667-240x180.jpeg"},{"imageLink":"https://images.olx.com.pk/thumbnails/228711643-240x180.jpeg"},{"imageLink":"https://images.olx.com.pk/thumbnails/228711604-240x180.jpeg"},{"imageLink":"https://images.olx.com.pk/thumbnails/228596749-240x180.jpeg"},{"imageLink":"https://images.olx.com.pk/thumbnails/227745057-240x180.jpeg"},{"imageLink":"https://images.olx.com.pk/thumbnails/227498812-240x180.jpeg"},{"imageLink":"https://images.olx.com.pk/thumbnails/226660065-240x180.jpeg"},{"imageLink":"https://images.olx.com.pk/thumbnails/227899446-240x180.jpeg"},{"imageLink":"https://images.olx.com.pk/thumbnails/217593602-240x180.jpeg"},{"imageLink":"https://images.olx.com.pk/thumbnails/228711428-240x180.jpeg"},{"imageLink":"https://images.olx.com.pk/thumbnails/228711276-240x180.jpeg"},{"imageLink":"https://images.olx.com.pk/thumbnails/228711249-240x180.jpeg"},{"imageLink":"https://images.olx.com.pk/thumbnails/228711235-240x180.jpeg"},{"imageLink":"https://images.olx.com.pk/thumbnails/228711197-240x180.jpeg"},{"imageLink":"https://images.olx.com.pk/thumbnails/228711156-240x180.jpeg"},{"imageLink":"https://images.olx.com.pk/thumbnails/228711039-240x180.jpeg"},{"imageLink":"https://images.olx.com.pk/thumbnails/228711021-240x180.jpeg"},{"imageLink":"https://images.olx.com.pk/thumbnails/228710957-240x180.jpeg"},{"imageLink":"https://images.olx.com.pk/thumbnails/228710940-240x180.jpeg"},{"imageLink":"https://images.olx.com.pk/thumbnails/228710924-240x180.jpeg"},{"imageLink":"https://images.olx.com.pk/thumbnails/227748246-240x180.jpeg"},{"imageLink":"https://images.olx.com.pk/thumbnails/228710807-240x180.jpeg"},{"imageLink":"https://images.olx.com.pk/thumbnails/228710796-240x180.jpeg"},{"imageLink":"https://images.olx.com.pk/thumbnails/213674242-240x180.jpeg"},{"imageLink":"https://images.olx.com.pk/thumbnails/228032495-240x180.jpeg"},{"imageLink":"https://images.olx.com.pk/thumbnails/226963608-240x180.jpeg"},{"imageLink":"https://images.olx.com.pk/thumbnails/225931822-240x180.jpeg"},{"imageLink":"https://images.olx.com.pk/thumbnails/227179659-240x180.jpeg"},{"imageLink":"https://images.olx.com.pk/thumbnails/226389616-240x180.jpeg"},{"imageLink":"https://images.olx.com.pk/thumbnails/228710796-240x180.jpeg"},{"imageLink":"https://images.olx.com.pk/thumbnails/228710683-240x180.jpeg"},{"imageLink":"https://images.olx.com.pk/thumbnails/228710638-240x180.jpeg"},{"imageLink":"https://images.olx.com.pk/thumbnails/228710530-240x180.jpeg"},{"imageLink":"https://images.olx.com.pk/thumbnails/228710513-240x180.jpeg"},{"imageLink":"https://images.olx.com.pk/thumbnails/228710492-240x180.jpeg"},{"imageLink":"https://images.olx.com.pk/thumbnails/228705519-240x180.jpeg"},{"imageLink":"https://images.olx.com.pk/thumbnails/213969301-240x180.jpeg"},{"imageLink":"https://images.olx.com.pk/thumbnails/170978088-240x180.jpeg"},{"imageLink":"https://images.olx.com.pk/thumbnails/107621522-240x180.jpeg"},{"imageLink":"https://images.olx.com.pk/thumbnails/140351700-240x180.jpeg"},{"imageLink":"https://images.olx.com.pk/thumbnails/138153632-240x180.jpeg"},{"imageLink":"https://images.olx.com.pk/thumbnails/228710318-240x180.jpeg"},{"imageLink":"https://images.olx.com.pk/thumbnails/228710252-240x180.jpeg"},{"imageLink":"https://images.olx.com.pk/thumbnails/227412311-240x180.jpeg"},{"imageLink":"https://images.olx.com.pk/thumbnails/227498812-240x180.jpeg"},{"imageLink":"https://images.olx.com.pk/thumbnails/228354392-240x180.jpeg"},{"imageLink":"https://images.olx.com.pk/thumbnails/225861777-240x180.jpeg"},{"imageLink":"https://images.olx.com.pk/thumbnails/228233385-240x180.jpeg"},{"imageLink":"https://images.olx.com.pk/thumbnails/226544313-240x180.jpeg"},{"imageLink":"https://images.olx.com.pk/thumbnails/140351700-240x180.jpeg"},{"imageLink":"https://images.olx.com.pk/thumbnails/138153632-240x180.jpeg"},{"imageLink":"https://images.olx.com.pk/thumbnails/228710318-240x180.jpeg"},{"imageLink":"https://images.olx.com.pk/thumbnails/228710252-240x180.jpeg"},{"imageLink":"https://images.olx.com.pk/thumbnails/228710237-240x180.jpeg"},{"imageLink":"https://images.olx.com.pk/thumbnails/228710162-240x180.jpeg"},{"imageLink":"https://images.olx.com.pk/thumbnails/228710142-240x180.jpeg"},{"imageLink":"https://images.olx.com.pk/thumbnails/228710090-240x180.jpeg"},{"imageLink":"https://images.olx.com.pk/thumbnails/228710021-240x180.jpeg"},{"imageLink":"https://images.olx.com.pk/thumbnails/228710014-240x180.jpeg"},{"imageLink":"https://images.olx.com.pk/thumbnails/228709997-240x180.jpeg"},{"imageLink":"https://images.olx.com.pk/thumbnails/228709880-240x180.jpeg"},{"imageLink":"https://images.olx.com.pk/thumbnails/228709740-240x180.jpeg"},{"imageLink":"https://images.olx.com.pk/thumbnails/228709122-240x180.jpeg"},{"imageLink":"https://images.olx.com.pk/thumbnails/227202331-240x180.jpeg"},{"imageLink":"https://images.olx.com.pk/thumbnails/223240651-240x180.jpeg"},{"imageLink":"https://images.olx.com.pk/thumbnails/227235267-240x180.jpeg"},{"imageLink":"https://images.olx.com.pk/thumbnails/225677691-240x180.jpeg"},{"imageLink":"https://images.olx.com.pk/thumbnails/225913031-240x180.jpeg"},{"imageLink":"https://images.olx.com.pk/thumbnails/227974835-240x180.jpeg"},{"imageLink":"https://images.olx.com.pk/thumbnails/228709740-240x180.jpeg"},{"imageLink":"https://images.olx.com.pk/thumbnails/228709122-240x180.jpeg"},{"imageLink":"https://images.olx.com.pk/thumbnails/226719909-240x180.jpeg"},{"imageLink":"https://images.olx.com.pk/thumbnails/222972773-240x180.jpeg"},{"imageLink":"https://images.olx.com.pk/thumbnails/220542036-240x180.jpeg"},{"imageLink":"https://images.olx.com.pk/thumbnails/208798804-240x180.jpeg"},{"imageLink":"https://images.olx.com.pk/thumbnails/203212822-240x180.jpeg"},{"imageLink":"https://images.olx.com.pk/thumbnails/164093036-240x180.jpeg"},{"imageLink":"https://images.olx.com.pk/thumbnails/228709575-240x180.jpeg"},{"imageLink":"https://images.olx.com.pk/thumbnails/228709556-240x180.jpeg"},{"imageLink":"https://images.olx.com.pk/thumbnails/228709495-240x180.jpeg"},{"imageLink":"https://images.olx.com.pk/thumbnails/228709485-240x180.jpeg"},{"imageLink":"https://images.olx.com.pk/thumbnails/228709425-240x180.jpeg"},{"imageLink":"https://images.olx.com.pk/thumbnails/228709424-240x180.jpeg"},{"imageLink":"https://images.olx.com.pk/thumbnails/226112567-240x180.jpeg"},{"imageLink":"https://images.olx.com.pk/thumbnails/223730107-240x180.jpeg"},{"imageLink":"https://images.olx.com.pk/thumbnails/225154486-240x180.jpeg"},{"imageLink":"https://images.olx.com.pk/thumbnails/221660852-240x180.jpeg"},{"imageLink":"https://images.olx.com.pk/thumbnails/223521385-240x180.jpeg"},{"imageLink":"https://images.olx.com.pk/thumbnails/226629864-240x180.jpeg"},{"imageLink":"https://images.olx.com.pk/thumbnails/228709424-240x180.jpeg"},{"imageLink":"https://images.olx.com.pk/thumbnails/228709309-240x180.jpeg"},{"imageLink":"https://images.olx.com.pk/thumbnails/228709089-240x180.jpeg"},{"imageLink":"https://images.olx.com.pk/thumbnails/228709051-240x180.jpeg"},{"imageLink":"https://images.olx.com.pk/thumbnails/228708870-240x180.jpeg"},{"imageLink":"https://images.olx.com.pk/thumbnails/228708737-240x180.jpeg"},{"imageLink":"https://images.olx.com.pk/thumbnails/228708603-240x180.jpeg"},{"imageLink":"https://images.olx.com.pk/thumbnails/228708564-240x180.jpeg"},{"imageLink":"https://images.olx.com.pk/thumbnails/226719095-240x180.jpeg"},{"imageLink":"https://images.olx.com.pk/thumbnails/226718708-240x180.jpeg"},{"imageLink":"https://images.olx.com.pk/thumbnails/222838549-240x180.jpeg"},{"imageLink":"https://images.olx.com.pk/thumbnails/228708476-240x180.jpeg"},{"imageLink":"https://images.olx.com.pk/thumbnails/228708413-240x180.jpeg"},{"imageLink":"https://images.olx.com.pk/thumbnails/228708343-240x180.jpeg"},{"imageLink":"https://images.olx.com.pk/thumbnails/224697338-240x180.jpeg"},{"imageLink":"https://images.olx.com.pk/thumbnails/227763367-240x180.jpeg"},{"imageLink":"https://images.olx.com.pk/thumbnails/228683784-240x180.jpeg"},{"imageLink":"https://images.olx.com.pk/thumbnails/227423071-240x180.jpeg"},{"imageLink":"https://images.olx.com.pk/thumbnails/218542302-240x180.jpeg"},{"imageLink":"https://images.olx.com.pk/thumbnails/228590031-240x180.jpeg"},{"imageLink":"https://images.olx.com.pk/thumbnails/228708343-240x180.jpeg"},{"imageLink":"https://images.olx.com.pk/thumbnails/228708202-240x180.jpeg"},{"imageLink":"https://images.olx.com.pk/thumbnails/228707985-240x180.jpeg"},{"imageLink":"https://images.olx.com.pk/thumbnails/228707967-240x180.jpeg"},{"imageLink":"https://images.olx.com.pk/thumbnails/228707915-240x180.jpeg"},{"imageLink":"https://images.olx.com.pk/thumbnails/228708499-240x180.jpeg"},{"imageLink":"https://images.olx.com.pk/thumbnails/228707722-240x180.jpeg"},{"imageLink":"https://images.olx.com.pk/thumbnails/228707675-240x180.jpeg"},{"imageLink":"https://images.olx.com.pk/thumbnails/228707596-240x180.jpeg"},{"imageLink":"https://images.olx.com.pk/thumbnails/228707552-240x180.jpeg"},{"imageLink":"https://images.olx.com.pk/thumbnails/228707509-240x180.jpeg"},{"imageLink":"https://images.olx.com.pk/thumbnails/228707372-240x180.jpeg"},{"imageLink":"https://images.olx.com.pk/thumbnails/228707322-240x180.jpeg"},{"imageLink":"https://images.olx.com.pk/thumbnails/228707310-240x180.jpeg"},{"imageLink":"https://images.olx.com.pk/thumbnails/227486169-240x180.jpeg"},{"imageLink":"https://images.olx.com.pk/thumbnails/226903698-240x180.jpeg"},{"imageLink":"https://images.olx.com.pk/thumbnails/224958684-240x180.jpeg"},{"imageLink":"https://images.olx.com.pk/thumbnails/224561977-240x180.jpeg"},{"imageLink":"https://images.olx.com.pk/thumbnails/226707522-240x180.jpeg"},{"imageLink":"https://images.olx.com.pk/thumbnails/226544313-240x180.jpeg"},{"imageLink":"https://images.olx.com.pk/thumbnails/228707322-240x180.jpeg"},{"imageLink":"https://images.olx.com.pk/thumbnails/228707310-240x180.jpeg"},{"imageLink":"https://images.olx.com.pk/thumbnails/228707222-240x180.jpeg"},{"imageLink":"https://images.olx.com.pk/thumbnails/228707201-240x180.jpeg"},{"imageLink":"https://images.olx.com.pk/thumbnails/228707169-240x180.jpeg"},{"imageLink":"https://images.olx.com.pk/thumbnails/201450417-240x180.jpeg"},{"imageLink":"https://images.olx.com.pk/thumbnails/228706915-240x180.jpeg"},{"imageLink":"https://images.olx.com.pk/thumbnails/228706898-240x180.jpeg"},{"imageLink":"https://images.olx.com.pk/thumbnails/228706802-240x180.jpeg"},{"imageLink":"https://images.olx.com.pk/thumbnails/228706645-240x180.jpeg"},{"imageLink":"https://images.olx.com.pk/thumbnails/228706619-240x180.jpeg"},{"imageLink":"https://images.olx.com.pk/thumbnails/228706561-240x180.jpeg"},{"imageLink":"https://images.olx.com.pk/thumbnails/228706421-240x180.jpeg"},{"imageLink":"https://images.olx.com.pk/thumbnails/228706377-240x180.jpeg"},{"imageLink":"https://images.olx.com.pk/thumbnails/225930194-240x180.jpeg"},{"imageLink":"https://images.olx.com.pk/thumbnails/227186132-240x180.jpeg"},{"imageLink":"https://images.olx.com.pk/thumbnails/222775126-240x180.jpeg"},{"imageLink":"https://images.olx.com.pk/thumbnails/226269697-240x180.jpeg"},{"imageLink":"https://images.olx.com.pk/thumbnails/226980596-240x180.jpeg"},{"imageLink":"https://images.olx.com.pk/thumbnails/227988112-240x180.jpeg"},{"imageLink":"https://images.olx.com.pk/thumbnails/228703351-240x180.jpeg"},{"imageLink":"https://images.olx.com.pk/thumbnails/220447008-240x180.jpeg"},{"imageLink":"https://images.olx.com.pk/thumbnails/228706137-240x180.jpeg"},{"imageLink":"https://images.olx.com.pk/thumbnails/228705987-240x180.jpeg"},{"imageLink":"https://images.olx.com.pk/thumbnails/228705958-240x180.jpeg"},{"imageLink":"https://images.olx.com.pk/thumbnails/228705853-240x180.jpeg"},{"imageLink":"https://images.olx.com.pk/thumbnails/228705695-240x180.jpeg"},{"imageLink":"https://images.olx.com.pk/thumbnails/222365366-240x180.jpeg"},{"imageLink":"https://images.olx.com.pk/thumbnails/228705592-240x180.jpeg"},{"imageLink":"https://images.olx.com.pk/thumbnails/228705466-240x180.jpeg"},{"imageLink":"https://images.olx.com.pk/thumbnails/228705455-240x180.jpeg"},{"imageLink":"https://images.olx.com.pk/thumbnails/228705445-240x180.jpeg"},{"imageLink":"https://images.olx.com.pk/thumbnails/228705440-240x180.jpeg"},{"imageLink":"https://images.olx.com.pk/thumbnails/228705357-240x180.jpeg"},{"imageLink":"https://images.olx.com.pk/thumbnails/224144964-240x180.jpeg"},{"imageLink":"https://images.olx.com.pk/thumbnails/226557018-240x180.jpeg"},{"imageLink":"https://images.olx.com.pk/thumbnails/226405107-240x180.jpeg"},{"imageLink":"https://images.olx.com.pk/thumbnails/227397065-240x180.jpeg"},{"imageLink":"https://images.olx.com.pk/thumbnails/226540178-240x180.jpeg"},{"imageLink":"https://images.olx.com.pk/thumbnails/227914074-240x180.jpeg"},{"imageLink":"https://images.olx.com.pk/thumbnails/228705254-240x180.jpeg"},{"imageLink":"https://images.olx.com.pk/thumbnails/228705128-240x180.jpeg"},{"imageLink":"https://images.olx.com.pk/thumbnails/228705073-240x180.jpeg"},{"imageLink":"https://images.olx.com.pk/thumbnails/228704820-240x180.jpeg"},{"imageLink":"https://images.olx.com.pk/thumbnails/228704806-240x180.jpeg"},{"imageLink":"https://images.olx.com.pk/thumbnails/228704722-240x180.jpeg"},{"imageLink":"https://images.olx.com.pk/thumbnails/228704654-240x180.jpeg"},{"imageLink":"https://images.olx.com.pk/thumbnails/228704619-240x180.jpeg"},{"imageLink":"https://images.olx.com.pk/thumbnails/228704450-240x180.jpeg"},{"imageLink":"https://images.olx.com.pk/thumbnails/196152235-240x180.jpeg"},{"imageLink":"https://images.olx.com.pk/thumbnails/228704337-240x180.jpeg"},{"imageLink":"https://images.olx.com.pk/thumbnails/228704285-240x180.jpeg"},{"imageLink":"https://images.olx.com.pk/thumbnails/228704140-240x180.jpeg"},{"imageLink":"https://images.olx.com.pk/thumbnails/228704079-240x180.jpeg"},{"imageLink":"https://images.olx.com.pk/thumbnails/224944036-240x180.jpeg"},{"imageLink":"https://images.olx.com.pk/thumbnails/228226842-240x180.jpeg"},{"imageLink":"https://images.olx.com.pk/thumbnails/228234204-240x180.jpeg"},{"imageLink":"https://images.olx.com.pk/thumbnails/223349786-240x180.jpeg"},{"imageLink":"https://images.olx.com.pk/thumbnails/226611881-240x180.jpeg"},{"imageLink":"https://images.olx.com.pk/thumbnails/225873500-240x180.jpeg"},{"imageLink":"https://images.olx.com.pk/thumbnails/228704079-240x180.jpeg"},{"imageLink":"https://images.olx.com.pk/thumbnails/228704039-240x180.jpeg"},{"imageLink":"https://images.olx.com.pk/thumbnails/228703991-240x180.jpeg"},{"imageLink":"https://images.olx.com.pk/thumbnails/228703900-240x180.jpeg"},{"imageLink":"https://images.olx.com.pk/thumbnails/228703800-240x180.jpeg"},{"imageLink":"https://images.olx.com.pk/thumbnails/228703728-240x180.jpeg"},{"imageLink":"https://images.olx.com.pk/thumbnails/228703698-240x180.jpeg"},{"imageLink":"https://images.olx.com.pk/thumbnails/228703642-240x180.jpeg"},{"imageLink":"https://images.olx.com.pk/thumbnails/216180193-240x180.jpeg"},{"imageLink":"https://images.olx.com.pk/thumbnails/215470413-240x180.jpeg"},{"imageLink":"https://images.olx.com.pk/thumbnails/228703548-240x180.jpeg"},{"imageLink":"https://images.olx.com.pk/thumbnails/228703541-240x180.jpeg"},{"imageLink":"https://images.olx.com.pk/thumbnails/228703476-240x180.jpeg"},{"imageLink":"https://images.olx.com.pk/thumbnails/228703330-240x180.jpeg"},{"imageLink":"https://images.olx.com.pk/thumbnails/223503693-240x180.jpeg"},{"imageLink":"https://images.olx.com.pk/thumbnails/216606171-240x180.jpeg"},{"imageLink":"https://images.olx.com.pk/thumbnails/209891382-240x180.jpeg"},{"imageLink":"https://images.olx.com.pk/thumbnails/226411372-240x180.jpeg"},{"imageLink":"https://images.olx.com.pk/thumbnails/228081513-240x180.jpeg"},{"imageLink":"https://images.olx.com.pk/thumbnails/228669499-240x180.jpeg"},{"imageLink":"https://images.olx.com.pk/thumbnails/228703330-240x180.jpeg"},{"imageLink":"https://images.olx.com.pk/thumbnails/228703309-240x180.jpeg"},{"imageLink":"https://images.olx.com.pk/thumbnails/228703248-240x180.jpeg"},{"imageLink":"https://images.olx.com.pk/thumbnails/228703194-240x180.jpeg"},{"imageLink":"https://images.olx.com.pk/thumbnails/228703106-240x180.jpeg"},{"imageLink":"https://images.olx.com.pk/thumbnails/227181401-240x180.jpeg"},{"imageLink":"https://images.olx.com.pk/thumbnails/228703016-240x180.jpeg"},{"imageLink":"https://images.olx.com.pk/thumbnails/228702910-240x180.jpeg"},{"imageLink":"https://images.olx.com.pk/thumbnails/228702828-240x180.jpeg"},{"imageLink":"https://images.olx.com.pk/thumbnails/228702814-240x180.jpeg"},{"imageLink":"https://images.olx.com.pk/thumbnails/228702784-240x180.jpeg"},{"imageLink":"https://images.olx.com.pk/thumbnails/228702781-240x180.jpeg"},{"imageLink":"https://images.olx.com.pk/thumbnails/228702751-240x180.jpeg"},{"imageLink":"https://images.olx.com.pk/thumbnails/228702713-240x180.jpeg"},{"imageLink":"https://images.olx.com.pk/thumbnails/219484520-240x180.jpeg"},{"imageLink":"https://images.olx.com.pk/thumbnails/228503303-240x180.jpeg"},{"imageLink":"https://images.olx.com.pk/thumbnails/225813874-240x180.jpeg"},{"imageLink":"https://images.olx.com.pk/thumbnails/224188218-240x180.jpeg"},{"imageLink":"https://images.olx.com.pk/thumbnails/227961221-240x180.jpeg"},{"imageLink":"https://images.olx.com.pk/thumbnails/223485363-240x180.jpeg"},{"imageLink":"https://images.olx.com.pk/thumbnails/228702713-240x180.jpeg"},{"imageLink":"https://images.olx.com.pk/thumbnails/228702648-240x180.jpeg"},{"imageLink":"https://images.olx.com.pk/thumbnails/228702634-240x180.jpeg"},{"imageLink":"https://images.olx.com.pk/thumbnails/228702576-240x180.jpeg"},{"imageLink":"https://images.olx.com.pk/thumbnails/228702554-240x180.jpeg"},{"imageLink":"https://images.olx.com.pk/thumbnails/228702526-240x180.jpeg"},{"imageLink":"https://images.olx.com.pk/thumbnails/228702409-240x180.jpeg"},{"imageLink":"https://images.olx.com.pk/thumbnails/227688437-240x180.jpeg"},{"imageLink":"https://images.olx.com.pk/thumbnails/225683135-240x180.jpeg"},{"imageLink":"https://images.olx.com.pk/thumbnails/228702110-240x180.jpeg"},{"imageLink":"https://images.olx.com.pk/thumbnails/228701781-240x180.jpeg"},{"imageLink":"https://images.olx.com.pk/thumbnails/208817134-240x180.jpeg"},{"imageLink":"https://images.olx.com.pk/thumbnails/228701762-240x180.jpeg"},{"imageLink":"https://images.olx.com.pk/thumbnails/228701652-240x180.jpeg"},{"imageLink":"https://images.olx.com.pk/thumbnails/226452043-240x180.jpeg"},{"imageLink":"https://images.olx.com.pk/thumbnails/220415232-240x180.jpeg"},{"imageLink":"https://images.olx.com.pk/thumbnails/227672923-240x180.jpeg"},{"imageLink":"https://images.olx.com.pk/thumbnails/225303053-240x180.jpeg"},{"imageLink":"https://images.olx.com.pk/thumbnails/156093586-240x180.jpeg"},{"imageLink":"https://images.olx.com.pk/thumbnails/228546364-240x180.jpeg"},{"imageLink":"https://images.olx.com.pk/thumbnails/228702409-240x180.jpeg"},{"imageLink":"https://images.olx.com.pk/thumbnails/227688437-240x180.jpeg"},{"imageLink":"https://images.olx.com.pk/thumbnails/225683135-240x180.jpeg"},{"imageLink":"https://images.olx.com.pk/thumbnails/228702110-240x180.jpeg"},{"imageLink":"https://images.olx.com.pk/thumbnails/228701781-240x180.jpeg"},{"imageLink":"https://images.olx.com.pk/thumbnails/208817134-240x180.jpeg"},{"imageLink":"https://images.olx.com.pk/thumbnails/228701762-240x180.jpeg"},{"imageLink":"https://images.olx.com.pk/thumbnails/228701652-240x180.jpeg"},{"imageLink":"https://images.olx.com.pk/thumbnails/228701519-240x180.jpeg"},{"imageLink":"https://images.olx.com.pk/thumbnails/228701470-240x180.jpeg"},{"imageLink":"https://images.olx.com.pk/thumbnails/228701458-240x180.jpeg"},{"imageLink":"https://images.olx.com.pk/thumbnails/228701454-240x180.jpeg"},{"imageLink":"https://images.olx.com.pk/thumbnails/228701418-240x180.jpeg"},{"imageLink":"https://images.olx.com.pk/thumbnails/228701181-240x180.jpeg"},{"imageLink":"https://images.olx.com.pk/thumbnails/227885087-240x180.jpeg"},{"imageLink":"https://images.olx.com.pk/thumbnails/228225176-240x180.jpeg"},{"imageLink":"https://images.olx.com.pk/thumbnails/225932904-240x180.jpeg"},{"imageLink":"https://images.olx.com.pk/thumbnails/226707522-240x180.jpeg"},{"imageLink":"https://images.olx.com.pk/thumbnails/227417856-240x180.jpeg"},{"imageLink":"https://images.olx.com.pk/thumbnails/227184030-240x180.jpeg"},{"imageLink":"https://images.olx.com.pk/thumbnails/227688437-240x180.jpeg"},{"imageLink":"https://images.olx.com.pk/thumbnails/225683135-240x180.jpeg"},{"imageLink":"https://images.olx.com.pk/thumbnails/228702110-240x180.jpeg"},{"imageLink":"https://images.olx.com.pk/thumbnails/228701781-240x180.jpeg"},{"imageLink":"https://images.olx.com.pk/thumbnails/208817134-240x180.jpeg"},{"imageLink":"https://images.olx.com.pk/thumbnails/228701762-240x180.jpeg"},{"imageLink":"https://images.olx.com.pk/thumbnails/228701652-240x180.jpeg"},{"imageLink":"https://images.olx.com.pk/thumbnails/228701519-240x180.jpeg"},{"imageLink":"https://images.olx.com.pk/thumbnails/228701470-240x180.jpeg"},{"imageLink":"https://images.olx.com.pk/thumbnails/228701458-240x180.jpeg"},{"imageLink":"https://images.olx.com.pk/thumbnails/228701454-240x180.jpeg"},{"imageLink":"https://images.olx.com.pk/thumbnails/228701418-240x180.jpeg"},{"imageLink":"https://images.olx.com.pk/thumbnails/228701181-240x180.jpeg"},{"imageLink":"https://images.olx.com.pk/thumbnails/228701142-240x180.jpeg"},{"imageLink":"https://images.olx.com.pk/thumbnails/228211365-240x180.jpeg"},{"imageLink":"https://images.olx.com.pk/thumbnails/227126019-240x180.jpeg"},{"imageLink":"https://images.olx.com.pk/thumbnails/228532839-240x180.jpeg"},{"imageLink":"https://images.olx.com.pk/thumbnails/227940136-240x180.jpeg"},{"imageLink":"https://images.olx.com.pk/thumbnails/226660065-240x180.jpeg"},{"imageLink":"https://images.olx.com.pk/thumbnails/228513057-240x180.jpeg"},{"imageLink":"https://images.olx.com.pk/thumbnails/228701142-240x180.jpeg"},{"imageLink":"https://images.olx.com.pk/thumbnails/228701118-240x180.jpeg"},{"imageLink":"https://images.olx.com.pk/thumbnails/228701105-240x180.jpeg"},{"imageLink":"https://images.olx.com.pk/thumbnails/228701095-240x180.jpeg"},{"imageLink":"https://images.olx.com.pk/thumbnails/228700939-240x180.jpeg"},{"imageLink":"https://images.olx.com.pk/thumbnails/228700759-240x180.jpeg"},{"imageLink":"https://images.olx.com.pk/thumbnails/228700719-240x180.jpeg"},{"imageLink":"https://images.olx.com.pk/thumbnails/228700686-240x180.jpeg"},{"imageLink":"https://images.olx.com.pk/thumbnails/228700603-240x180.jpeg"},{"imageLink":"https://images.olx.com.pk/thumbnails/228700548-240x180.jpeg"},{"imageLink":"https://images.olx.com.pk/thumbnails/222154143-240x180.jpeg"},{"imageLink":"https://images.olx.com.pk/thumbnails/228700385-240x180.jpeg"},{"imageLink":"https://images.olx.com.pk/thumbnails/228700372-240x180.jpeg"},{"imageLink":"https://images.olx.com.pk/thumbnails/228701307-240x180.jpeg"},{"imageLink":"https://images.olx.com.pk/thumbnails/227009113-240x180.jpeg"},{"imageLink":"https://images.olx.com.pk/thumbnails/228680630-240x180.jpeg"},{"imageLink":"https://images.olx.com.pk/thumbnails/227759578-240x180.jpeg"},{"imageLink":"https://images.olx.com.pk/thumbnails/228293398-240x180.jpeg"},{"imageLink":"https://images.olx.com.pk/thumbnails/226369142-240x180.jpeg"},{"imageLink":"https://images.olx.com.pk/thumbnails/216396496-240x180.jpeg"},{"imageLink":"https://images.olx.com.pk/thumbnails/228700229-240x180.jpeg"},{"imageLink":"https://images.olx.com.pk/thumbnails/228699851-240x180.jpeg"},{"imageLink":"https://images.olx.com.pk/thumbnails/228625435-240x180.jpeg"},{"imageLink":"https://images.olx.com.pk/thumbnails/211510058-240x180.jpeg"},{"imageLink":"https://images.olx.com.pk/thumbnails/228699691-240x180.jpeg"},{"imageLink":"https://images.olx.com.pk/thumbnails/228699654-240x180.jpeg"},{"imageLink":"https://images.olx.com.pk/thumbnails/228699526-240x180.jpeg"},{"imageLink":"https://images.olx.com.pk/thumbnails/228699398-240x180.jpeg"},{"imageLink":"https://images.olx.com.pk/thumbnails/228699308-240x180.jpeg"},{"imageLink":"https://images.olx.com.pk/thumbnails/228699241-240x180.jpeg"},{"imageLink":"https://images.olx.com.pk/thumbnails/228699144-240x180.jpeg"},{"imageLink":"https://images.olx.com.pk/thumbnails/228699124-240x180.jpeg"},{"imageLink":"https://images.olx.com.pk/thumbnails/228699098-240x180.jpeg"},{"imageLink":"https://images.olx.com.pk/thumbnails/228698909-240x180.jpeg"},{"imageLink":"https://images.olx.com.pk/thumbnails/226106792-240x180.jpeg"},{"imageLink":"https://images.olx.com.pk/thumbnails/227586467-240x180.jpeg"},{"imageLink":"https://images.olx.com.pk/thumbnails/227738617-240x180.jpeg"},{"imageLink":"https://images.olx.com.pk/thumbnails/228133779-240x180.jpeg"},{"imageLink":"https://images.olx.com.pk/thumbnails/225460799-240x180.jpeg"},{"imageLink":"https://images.olx.com.pk/thumbnails/222017960-240x180.jpeg"},{"imageLink":"https://images.olx.com.pk/thumbnails/228698909-240x180.jpeg"},{"imageLink":"https://images.olx.com.pk/thumbnails/228698768-240x180.jpeg"},{"imageLink":"https://images.olx.com.pk/thumbnails/228698726-240x180.jpeg"},{"imageLink":"https://images.olx.com.pk/thumbnails/228698720-240x180.jpeg"},{"imageLink":"https://images.olx.com.pk/thumbnails/228698632-240x180.jpeg"},{"imageLink":"https://images.olx.com.pk/thumbnails/228698612-240x180.jpeg"},{"imageLink":"https://images.olx.com.pk/thumbnails/228698590-240x180.jpeg"},{"imageLink":"https://images.olx.com.pk/thumbnails/219819328-240x180.jpeg"},{"imageLink":"https://images.olx.com.pk/thumbnails/228698519-240x180.jpeg"},{"imageLink":"https://images.olx.com.pk/thumbnails/228698477-240x180.jpeg"},{"imageLink":"https://images.olx.com.pk/thumbnails/228698370-240x180.jpeg"},{"imageLink":"https://images.olx.com.pk/thumbnails/228698337-240x180.jpeg"},{"imageLink":"https://images.olx.com.pk/thumbnails/228698309-240x180.jpeg"},{"imageLink":"https://images.olx.com.pk/thumbnails/228698100-240x180.jpeg"},{"imageLink":"https://images.olx.com.pk/thumbnails/226759391-240x180.jpeg"},{"imageLink":"https://images.olx.com.pk/thumbnails/228545144-240x180.jpeg"},{"imageLink":"https://images.olx.com.pk/thumbnails/227968928-240x180.jpeg"},{"imageLink":"https://images.olx.com.pk/thumbnails/226456195-240x180.jpeg"},{"imageLink":"https://images.olx.com.pk/thumbnails/228524751-240x180.jpeg"},{"imageLink":"https://images.olx.com.pk/thumbnails/219330853-240x180.jpeg"},{"imageLink":"https://images.olx.com.pk/thumbnails/228698100-240x180.jpeg"},{"imageLink":"https://images.olx.com.pk/thumbnails/228697979-240x180.jpeg"},{"imageLink":"https://images.olx.com.pk/thumbnails/228697872-240x180.jpeg"},{"imageLink":"https://images.olx.com.pk/thumbnails/228697816-240x180.jpeg"},{"imageLink":"https://images.olx.com.pk/thumbnails/228697793-240x180.jpeg"},{"imageLink":"https://images.olx.com.pk/thumbnails/228697646-240x180.jpeg"},{"imageLink":"https://images.olx.com.pk/thumbnails/228697590-240x180.jpeg"},{"imageLink":"https://images.olx.com.pk/thumbnails/228697342-240x180.jpeg"},{"imageLink":"https://images.olx.com.pk/thumbnails/228697327-240x180.jpeg"},{"imageLink":"https://images.olx.com.pk/thumbnails/228697308-240x180.jpeg"},{"imageLink":"https://images.olx.com.pk/thumbnails/228697277-240x180.jpeg"},{"imageLink":"https://images.olx.com.pk/thumbnails/214895162-240x180.jpeg"},{"imageLink":"https://images.olx.com.pk/thumbnails/228697144-240x180.jpeg"},{"imageLink":"https://images.olx.com.pk/thumbnails/228697077-240x180.jpeg"},{"imageLink":"https://images.olx.com.pk/thumbnails/228358107-240x180.jpeg"},{"imageLink":"https://images.olx.com.pk/thumbnails/226300279-240x180.jpeg"},{"imageLink":"https://images.olx.com.pk/thumbnails/225757826-240x180.jpeg"},{"imageLink":"https://images.olx.com.pk/thumbnails/226518958-240x180.jpeg"},{"imageLink":"https://images.olx.com.pk/thumbnails/227867556-240x180.jpeg"},{"imageLink":"https://images.olx.com.pk/thumbnails/226332686-240x180.jpeg"},{"imageLink":"https://images.olx.com.pk/thumbnails/228697077-240x180.jpeg"},{"imageLink":"https://images.olx.com.pk/thumbnails/228696999-240x180.jpeg"},{"imageLink":"https://images.olx.com.pk/thumbnails/228696955-240x180.jpeg"},{"imageLink":"https://images.olx.com.pk/thumbnails/228696929-240x180.jpeg"},{"imageLink":"https://images.olx.com.pk/thumbnails/228696923-240x180.jpeg"},{"imageLink":"https://images.olx.com.pk/thumbnails/228696891-240x180.jpeg"},{"imageLink":"https://images.olx.com.pk/thumbnails/228696877-240x180.jpeg"},{"imageLink":"https://images.olx.com.pk/thumbnails/228696770-240x180.jpeg"},{"imageLink":"https://images.olx.com.pk/thumbnails/228696706-240x180.jpeg"},{"imageLink":"https://images.olx.com.pk/thumbnails/228696693-240x180.jpeg"},{"imageLink":"https://images.olx.com.pk/thumbnails/228696645-240x180.jpeg"},{"imageLink":"https://images.olx.com.pk/thumbnails/228696623-240x180.jpeg"},{"imageLink":"https://images.olx.com.pk/thumbnails/228696525-240x180.jpeg"},{"imageLink":"https://images.olx.com.pk/thumbnails/228681711-240x180.jpeg"},{"imageLink":"https://images.olx.com.pk/thumbnails/227957541-240x180.jpeg"},{"imageLink":"https://images.olx.com.pk/thumbnails/226960649-240x180.jpeg"},{"imageLink":"https://images.olx.com.pk/thumbnails/228293398-240x180.jpeg"},{"imageLink":"https://images.olx.com.pk/thumbnails/228262743-240x180.jpeg"},{"imageLink":"https://images.olx.com.pk/thumbnails/225363686-240x180.jpeg"},{"imageLink":"https://images.olx.com.pk/thumbnails/222043196-240x180.jpeg"},{"imageLink":"https://images.olx.com.pk/thumbnails/228681711-240x180.jpeg"},{"imageLink":"https://images.olx.com.pk/thumbnails/225657304-240x180.jpeg"},{"imageLink":"https://images.olx.com.pk/thumbnails/228696479-240x180.jpeg"},{"imageLink":"https://images.olx.com.pk/thumbnails/228696351-240x180.jpeg"},{"imageLink":"https://images.olx.com.pk/thumbnails/228696331-240x180.jpeg"},{"imageLink":"https://images.olx.com.pk/thumbnails/228696272-240x180.jpeg"},{"imageLink":"https://images.olx.com.pk/thumbnails/228696178-240x180.jpeg"},{"imageLink":"https://images.olx.com.pk/thumbnails/228696109-240x180.jpeg"},{"imageLink":"https://images.olx.com.pk/thumbnails/228695933-240x180.jpeg"},{"imageLink":"https://images.olx.com.pk/thumbnails/228695923-240x180.jpeg"},{"imageLink":"https://images.olx.com.pk/thumbnails/228692677-240x180.jpeg"},{"imageLink":"https://images.olx.com.pk/thumbnails/220694106-240x180.jpeg"},{"imageLink":"https://images.olx.com.pk/thumbnails/205857905-240x180.jpeg"},{"imageLink":"https://images.olx.com.pk/thumbnails/228695740-240x180.jpeg"},{"imageLink":"https://images.olx.com.pk/thumbnails/225593769-240x180.jpeg"},{"imageLink":"https://images.olx.com.pk/thumbnails/227861772-240x180.jpeg"},{"imageLink":"https://images.olx.com.pk/thumbnails/190997682-240x180.jpeg"},{"imageLink":"https://images.olx.com.pk/thumbnails/225334628-240x180.jpeg"},{"imageLink":"https://images.olx.com.pk/thumbnails/227054820-240x180.jpeg"},{"imageLink":"https://images.olx.com.pk/thumbnails/227183207-240x180.jpeg"},{"imageLink":"https://images.olx.com.pk/thumbnails/228695722-240x180.jpeg"},{"imageLink":"https://images.olx.com.pk/thumbnails/228695648-240x180.jpeg"},{"imageLink":"https://images.olx.com.pk/thumbnails/228695630-240x180.jpeg"},{"imageLink":"https://images.olx.com.pk/thumbnails/228695595-240x180.jpeg"},{"imageLink":"https://images.olx.com.pk/thumbnails/228695473-240x180.jpeg"},{"imageLink":"https://images.olx.com.pk/thumbnails/228695433-240x180.jpeg"},{"imageLink":"https://images.olx.com.pk/thumbnails/228695365-240x180.jpeg"},{"imageLink":"https://images.olx.com.pk/thumbnails/228695360-240x180.jpeg"},{"imageLink":"https://images.olx.com.pk/thumbnails/228695324-240x180.jpeg"},{"imageLink":"https://images.olx.com.pk/thumbnails/228695145-240x180.jpeg"},{"imageLink":"https://images.olx.com.pk/thumbnails/228695141-240x180.jpeg"},{"imageLink":"https://images.olx.com.pk/thumbnails/228695059-240x180.jpeg"},{"imageLink":"https://images.olx.com.pk/thumbnails/228695051-240x180.jpeg"},{"imageLink":"https://images.olx.com.pk/thumbnails/228694954-240x180.jpeg"},{"imageLink":"https://images.olx.com.pk/thumbnails/222693932-240x180.jpeg"},{"imageLink":"https://images.olx.com.pk/thumbnails/228664154-240x180.jpeg"},{"imageLink":"https://images.olx.com.pk/thumbnails/226162656-240x180.jpeg"},{"imageLink":"https://images.olx.com.pk/thumbnails/223190368-240x180.jpeg"},{"imageLink":"https://images.olx.com.pk/thumbnails/220198998-240x180.jpeg"},{"imageLink":"https://images.olx.com.pk/thumbnails/227683297-240x180.jpeg"},{"imageLink":"https://images.olx.com.pk/thumbnails/228695059-240x180.jpeg"},{"imageLink":"https://images.olx.com.pk/thumbnails/228695051-240x180.jpeg"},{"imageLink":"https://images.olx.com.pk/thumbnails/228694954-240x180.jpeg"},{"imageLink":"https://images.olx.com.pk/thumbnails/228694793-240x180.jpeg"},{"imageLink":"https://images.olx.com.pk/thumbnails/228694712-240x180.jpeg"},{"imageLink":"https://images.olx.com.pk/thumbnails/228694682-240x180.jpeg"},{"imageLink":"https://images.olx.com.pk/thumbnails/228694643-240x180.jpeg"},{"imageLink":"https://images.olx.com.pk/thumbnails/228694532-240x180.jpeg"},{"imageLink":"https://images.olx.com.pk/thumbnails/228694475-240x180.jpeg"},{"imageLink":"https://images.olx.com.pk/thumbnails/228694446-240x180.jpeg"},{"imageLink":"https://images.olx.com.pk/thumbnails/228694430-240x180.jpeg"},{"imageLink":"https://images.olx.com.pk/thumbnails/228694420-240x180.jpeg"},{"imageLink":"https://images.olx.com.pk/thumbnails/228694410-240x180.jpeg"},{"imageLink":"https://images.olx.com.pk/thumbnails/228693856-240x180.jpeg"},{"imageLink":"https://images.olx.com.pk/thumbnails/227448128-240x180.jpeg"},{"imageLink":"https://images.olx.com.pk/thumbnails/228490927-240x180.jpeg"},{"imageLink":"https://images.olx.com.pk/thumbnails/226344124-240x180.jpeg"},{"imageLink":"https://images.olx.com.pk/thumbnails/225493235-240x180.jpeg"},{"imageLink":"https://images.olx.com.pk/thumbnails/227563796-240x180.jpeg"},{"imageLink":"https://images.olx.com.pk/thumbnails/228026784-240x180.jpeg"},{"imageLink":"https://images.olx.com.pk/thumbnails/228693729-240x180.jpeg"},{"imageLink":"https://images.olx.com.pk/thumbnails/228693717-240x180.jpeg"},{"imageLink":"https://images.olx.com.pk/thumbnails/228693657-240x180.jpeg"},{"imageLink":"https://images.olx.com.pk/thumbnails/228693627-240x180.jpeg"},{"imageLink":"https://images.olx.com.pk/thumbnails/228693593-240x180.jpeg"},{"imageLink":"https://images.olx.com.pk/thumbnails/228693525-240x180.jpeg"},{"imageLink":"https://images.olx.com.pk/thumbnails/228693335-240x180.jpeg"},{"imageLink":"https://images.olx.com.pk/thumbnails/228693233-240x180.jpeg"},{"imageLink":"https://images.olx.com.pk/thumbnails/228693228-240x180.jpeg"},{"imageLink":"https://images.olx.com.pk/thumbnails/228693110-240x180.jpeg"},{"imageLink":"https://images.olx.com.pk/thumbnails/228693101-240x180.jpeg"},{"imageLink":"https://images.olx.com.pk/thumbnails/228693062-240x180.jpeg"},{"imageLink":"https://images.olx.com.pk/thumbnails/228693003-240x180.jpeg"},{"imageLink":"https://images.olx.com.pk/thumbnails/228692987-240x180.jpeg"},{"imageLink":"https://images.olx.com.pk/thumbnails/228578854-240x180.jpeg"},{"imageLink":"https://images.olx.com.pk/thumbnails/224522721-240x180.jpeg"},{"imageLink":"https://images.olx.com.pk/thumbnails/224660305-240x180.jpeg"},{"imageLink":"https://images.olx.com.pk/thumbnails/222022342-240x180.jpeg"},{"imageLink":"https://images.olx.com.pk/thumbnails/226072241-240x180.jpeg"},{"imageLink":"https://images.olx.com.pk/thumbnails/227537362-240x180.jpeg"},{"imageLink":"https://images.olx.com.pk/thumbnails/228693062-240x180.jpeg"},{"imageLink":"https://images.olx.com.pk/thumbnails/228693003-240x180.jpeg"},{"imageLink":"https://images.olx.com.pk/thumbnails/228692987-240x180.jpeg"},{"imageLink":"https://images.olx.com.pk/thumbnails/228692923-240x180.jpeg"},{"imageLink":"https://images.olx.com.pk/thumbnails/228692897-240x180.jpeg"},{"imageLink":"https://images.olx.com.pk/thumbnails/228692809-240x180.jpeg"},{"imageLink":"https://images.olx.com.pk/thumbnails/228692779-240x180.jpeg"},{"imageLink":"https://images.olx.com.pk/thumbnails/228692723-240x180.jpeg"},{"imageLink":"https://images.olx.com.pk/thumbnails/228692713-240x180.jpeg"},{"imageLink":"https://images.olx.com.pk/thumbnails/228692396-240x180.jpeg"},{"imageLink":"https://images.olx.com.pk/thumbnails/223574222-240x180.jpeg"},{"imageLink":"https://images.olx.com.pk/thumbnails/228692559-240x180.jpeg"},{"imageLink":"https://images.olx.com.pk/thumbnails/228692302-240x180.jpeg"},{"imageLink":"https://images.olx.com.pk/thumbnails/228692225-240x180.jpeg"},{"imageLink":"https://images.olx.com.pk/thumbnails/226526367-240x180.jpeg"},{"imageLink":"https://images.olx.com.pk/thumbnails/225791281-240x180.jpeg"},{"imageLink":"https://images.olx.com.pk/thumbnails/220042355-240x180.jpeg"},{"imageLink":"https://images.olx.com.pk/thumbnails/228460750-240x180.jpeg"},{"imageLink":"https://images.olx.com.pk/thumbnails/224895353-240x180.jpeg"},{"imageLink":"https://images.olx.com.pk/thumbnails/224433660-240x180.jpeg"},{"imageLink":"https://images.olx.com.pk/thumbnails/228692225-240x180.jpeg"},{"imageLink":"https://images.olx.com.pk/thumbnails/228692171-240x180.jpeg"},{"imageLink":"https://images.olx.com.pk/thumbnails/228692162-240x180.jpeg"},{"imageLink":"https://images.olx.com.pk/thumbnails/228692140-240x180.jpeg"},{"imageLink":"https://images.olx.com.pk/thumbnails/228692015-240x180.jpeg"},{"imageLink":"https://images.olx.com.pk/thumbnails/223522841-240x180.jpeg"},{"imageLink":"https://images.olx.com.pk/thumbnails/216835746-240x180.jpeg"},{"imageLink":"https://images.olx.com.pk/thumbnails/228691853-240x180.jpeg"},{"imageLink":"https://images.olx.com.pk/thumbnails/228691844-240x180.jpeg"},{"imageLink":"https://images.olx.com.pk/thumbnails/228691696-240x180.jpeg"},{"imageLink":"https://images.olx.com.pk/thumbnails/228691633-240x180.jpeg"},{"imageLink":"https://images.olx.com.pk/thumbnails/228693672-240x180.jpeg"},{"imageLink":"https://images.olx.com.pk/thumbnails/228691304-240x180.jpeg"},{"imageLink":"https://images.olx.com.pk/thumbnails/228691279-240x180.jpeg"},{"imageLink":"https://images.olx.com.pk/thumbnails/224660305-240x180.jpeg"},{"imageLink":"https://images.olx.com.pk/thumbnails/226203974-240x180.jpeg"},{"imageLink":"https://images.olx.com.pk/thumbnails/227320895-240x180.jpeg"},{"imageLink":"https://images.olx.com.pk/thumbnails/220415232-240x180.jpeg"},{"imageLink":"https://images.olx.com.pk/thumbnails/228483830-240x180.jpeg"},{"imageLink":"https://images.olx.com.pk/thumbnails/228533517-240x180.jpeg"},{"imageLink":"https://images.olx.com.pk/thumbnails/228691279-240x180.jpeg"},{"imageLink":"https://images.olx.com.pk/thumbnails/228502396-240x180.jpeg"},{"imageLink":"https://images.olx.com.pk/thumbnails/205865829-240x180.jpeg"},{"imageLink":"https://images.olx.com.pk/thumbnails/228691138-240x180.jpeg"},{"imageLink":"https://images.olx.com.pk/thumbnails/228691105-240x180.jpeg"},{"imageLink":"https://images.olx.com.pk/thumbnails/228691045-240x180.jpeg"},{"imageLink":"https://images.olx.com.pk/thumbnails/228690866-240x180.jpeg"},{"imageLink":"https://images.olx.com.pk/thumbnails/228690851-240x180.jpeg"},{"imageLink":"https://images.olx.com.pk/thumbnails/228690777-240x180.jpeg"},{"imageLink":"https://images.olx.com.pk/thumbnails/228690697-240x180.jpeg"},{"imageLink":"https://images.olx.com.pk/thumbnails/220775727-240x180.jpeg"},{"imageLink":"https://images.olx.com.pk/thumbnails/216564684-240x180.jpeg"},{"imageLink":"https://images.olx.com.pk/thumbnails/228690575-240x180.jpeg"},{"imageLink":"https://images.olx.com.pk/thumbnails/228692575-240x180.jpeg"},{"imageLink":"https://images.olx.com.pk/thumbnails/228600453-240x180.jpeg"},{"imageLink":"https://images.olx.com.pk/thumbnails/223913479-240x180.jpeg"},{"imageLink":"https://images.olx.com.pk/thumbnails/227885087-240x180.jpeg"},{"imageLink":"https://images.olx.com.pk/thumbnails/224603767-240x180.jpeg"},{"imageLink":"https://images.olx.com.pk/thumbnails/228299438-240x180.jpeg"},{"imageLink":"https://images.olx.com.pk/thumbnails/223444290-240x180.jpeg"},{"imageLink":"https://images.olx.com.pk/thumbnails/228690198-240x180.jpeg"},{"imageLink":"https://images.olx.com.pk/thumbnails/228690046-240x180.jpeg"},{"imageLink":"https://images.olx.com.pk/thumbnails/228690013-240x180.jpeg"},{"imageLink":"https://images.olx.com.pk/thumbnails/228689945-240x180.jpeg"},{"imageLink":"https://images.olx.com.pk/thumbnails/228689930-240x180.jpeg"},{"imageLink":"https://images.olx.com.pk/thumbnails/228689857-240x180.jpeg"},{"imageLink":"https://images.olx.com.pk/thumbnails/228689721-240x180.jpeg"},{"imageLink":"https://images.olx.com.pk/thumbnails/228689580-240x180.jpeg"},{"imageLink":"https://images.olx.com.pk/thumbnails/228689492-240x180.jpeg"},{"imageLink":"https://images.olx.com.pk/thumbnails/226632518-240x180.jpeg"},{"imageLink":"https://images.olx.com.pk/thumbnails/228689307-240x180.jpeg"},{"imageLink":"https://images.olx.com.pk/thumbnails/228689275-240x180.jpeg"},{"imageLink":"https://images.olx.com.pk/thumbnails/228689181-240x180.jpeg"},{"imageLink":"https://images.olx.com.pk/thumbnails/228689134-240x180.jpeg"},{"imageLink":"https://images.olx.com.pk/thumbnails/227009113-240x180.jpeg"},{"imageLink":"https://images.olx.com.pk/thumbnails/228598810-240x180.jpeg"},{"imageLink":"https://images.olx.com.pk/thumbnails/224895353-240x180.jpeg"},{"imageLink":"https://images.olx.com.pk/thumbnails/209328538-240x180.jpeg"},{"imageLink":"https://images.olx.com.pk/thumbnails/225873500-240x180.jpeg"},{"imageLink":"https://images.olx.com.pk/thumbnails/228352478-240x180.jpeg"},{"imageLink":"https://images.olx.com.pk/thumbnails/228688904-240x180.jpeg"},{"imageLink":"https://images.olx.com.pk/thumbnails/228688782-240x180.jpeg"},{"imageLink":"https://images.olx.com.pk/thumbnails/228718597-240x180.jpeg"},{"imageLink":"https://images.olx.com.pk/thumbnails/228688634-240x180.jpeg"},{"imageLink":"https://images.olx.com.pk/thumbnails/228688621-240x180.jpeg"},{"imageLink":"https://images.olx.com.pk/thumbnails/228688565-240x180.jpeg"},{"imageLink":"https://images.olx.com.pk/thumbnails/228688215-240x180.jpeg"},{"imageLink":"https://images.olx.com.pk/thumbnails/228688186-240x180.jpeg"},{"imageLink":"https://images.olx.com.pk/thumbnails/213167884-240x180.jpeg"},{"imageLink":"https://images.olx.com.pk/thumbnails/228688017-240x180.jpeg"},{"imageLink":"https://images.olx.com.pk/thumbnails/228687975-240x180.jpeg"},{"imageLink":"https://images.olx.com.pk/thumbnails/228687918-240x180.jpeg"},{"imageLink":"https://images.olx.com.pk/thumbnails/228687813-240x180.jpeg"},{"imageLink":"https://images.olx.com.pk/thumbnails/228687786-240x180.jpeg"},{"imageLink":"https://images.olx.com.pk/thumbnails/228649654-240x180.jpeg"},{"imageLink":"https://images.olx.com.pk/thumbnails/205506691-240x180.jpeg"},{"imageLink":"https://images.olx.com.pk/thumbnails/228038135-240x180.jpeg"},{"imageLink":"https://images.olx.com.pk/thumbnails/228322416-240x180.jpeg"},{"imageLink":"https://images.olx.com.pk/thumbnails/224231990-240x180.jpeg"},{"imageLink":"https://images.olx.com.pk/thumbnails/227202331-240x180.jpeg"},{"imageLink":"https://images.olx.com.pk/thumbnails/228687569-240x180.jpeg"},{"imageLink":"https://images.olx.com.pk/thumbnails/228687439-240x180.jpeg"},{"imageLink":"https://images.olx.com.pk/thumbnails/220746558-240x180.jpeg"},{"imageLink":"https://images.olx.com.pk/thumbnails/228687271-240x180.jpeg"},{"imageLink":"https://images.olx.com.pk/thumbnails/228687131-240x180.jpeg"},{"imageLink":"https://images.olx.com.pk/thumbnails/228687037-240x180.jpeg"},{"imageLink":"https://images.olx.com.pk/thumbnails/228686949-240x180.jpeg"},{"imageLink":"https://images.olx.com.pk/thumbnails/228686835-240x180.jpeg"},{"imageLink":"https://images.olx.com.pk/thumbnails/228686812-240x180.jpeg"},{"imageLink":"https://images.olx.com.pk/thumbnails/228686736-240x180.jpeg"},{"imageLink":"https://images.olx.com.pk/thumbnails/228686712-240x180.jpeg"},{"imageLink":"https://images.olx.com.pk/thumbnails/228686700-240x180.jpeg"},{"imageLink":"https://images.olx.com.pk/thumbnails/228686662-240x180.jpeg"},{"imageLink":"https://images.olx.com.pk/thumbnails/228686526-240x180.jpeg"},{"imageLink":"https://images.olx.com.pk/thumbnails/225048928-240x180.jpeg"},{"imageLink":"https://images.olx.com.pk/thumbnails/225262783-240x180.jpeg"},{"imageLink":"https://images.olx.com.pk/thumbnails/225427760-240x180.jpeg"},{"imageLink":"https://images.olx.com.pk/thumbnails/225880177-240x180.jpeg"},{"imageLink":"https://images.olx.com.pk/thumbnails/224895353-240x180.jpeg"},{"imageLink":"https://images.olx.com.pk/thumbnails/223343785-240x180.jpeg"},{"imageLink":"https://images.olx.com.pk/thumbnails/228686445-240x180.jpeg"},{"imageLink":"https://images.olx.com.pk/thumbnails/228686338-240x180.jpeg"},{"imageLink":"https://images.olx.com.pk/thumbnails/228686293-240x180.jpeg"},{"imageLink":"https://images.olx.com.pk/thumbnails/228686264-240x180.jpeg"},{"imageLink":"https://images.olx.com.pk/thumbnails/228686205-240x180.jpeg"},{"imageLink":"https://images.olx.com.pk/thumbnails/228686029-240x180.jpeg"},{"imageLink":"https://images.olx.com.pk/thumbnails/228685986-240x180.jpeg"},{"imageLink":"https://images.olx.com.pk/thumbnails/228685966-240x180.jpeg"},{"imageLink":"https://images.olx.com.pk/thumbnails/228697508-240x180.jpeg"},{"imageLink":"https://images.olx.com.pk/thumbnails/228685917-240x180.jpeg"},{"imageLink":"https://images.olx.com.pk/thumbnails/228491685-240x180.jpeg"},{"imageLink":"https://images.olx.com.pk/thumbnails/217444216-240x180.jpeg"},{"imageLink":"https://images.olx.com.pk/thumbnails/213018546-240x180.jpeg"},{"imageLink":"https://images.olx.com.pk/thumbnails/228685822-240x180.jpeg"},{"imageLink":"https://images.olx.com.pk/thumbnails/226544313-240x180.jpeg"},{"imageLink":"https://images.olx.com.pk/thumbnails/228492839-240x180.jpeg"},{"imageLink":"https://images.olx.com.pk/thumbnails/228376052-240x180.jpeg"},{"imageLink":"https://images.olx.com.pk/thumbnails/224263199-240x180.jpeg"},{"imageLink":"https://images.olx.com.pk/thumbnails/226114313-240x180.jpeg"},{"imageLink":"https://images.olx.com.pk/thumbnails/227552269-240x180.jpeg"},{"imageLink":"https://images.olx.com.pk/thumbnails/228685814-240x180.jpeg"},{"imageLink":"https://images.olx.com.pk/thumbnails/228685735-240x180.jpeg"},{"imageLink":"https://images.olx.com.pk/thumbnails/228685692-240x180.jpeg"},{"imageLink":"https://images.olx.com.pk/thumbnails/228685586-240x180.jpeg"},{"imageLink":"https://images.olx.com.pk/thumbnails/228685539-240x180.jpeg"},{"imageLink":"https://images.olx.com.pk/thumbnails/228685281-240x180.jpeg"},{"imageLink":"https://images.olx.com.pk/thumbnails/226835858-240x180.jpeg"},{"imageLink":"https://images.olx.com.pk/thumbnails/218880254-240x180.jpeg"},{"imageLink":"https://images.olx.com.pk/thumbnails/211677095-240x180.jpeg"},{"imageLink":"https://images.olx.com.pk/thumbnails/228685241-240x180.jpeg"},{"imageLink":"https://images.olx.com.pk/thumbnails/228685166-240x180.jpeg"},{"imageLink":"https://images.olx.com.pk/thumbnails/228685118-240x180.jpeg"},{"imageLink":"https://images.olx.com.pk/thumbnails/228685079-240x180.jpeg"},{"imageLink":"https://images.olx.com.pk/thumbnails/228684779-240x180.jpeg"},{"imageLink":"https://images.olx.com.pk/thumbnails/228353797-240x180.jpeg"},{"imageLink":"https://images.olx.com.pk/thumbnails/225474928-240x180.jpeg"},{"imageLink":"https://images.olx.com.pk/thumbnails/221629583-240x180.jpeg"},{"imageLink":"https://images.olx.com.pk/thumbnails/226907817-240x180.jpeg"},{"imageLink":"https://images.olx.com.pk/thumbnails/226567057-240x180.jpeg"},{"imageLink":"https://images.olx.com.pk/thumbnails/225728046-240x180.jpeg"},{"imageLink":"https://images.olx.com.pk/thumbnails/228684634-240x180.jpeg"},{"imageLink":"https://images.olx.com.pk/thumbnails/228382879-240x180.jpeg"},{"imageLink":"https://images.olx.com.pk/thumbnails/228684494-240x180.jpeg"},{"imageLink":"https://images.olx.com.pk/thumbnails/228684442-240x180.jpeg"},{"imageLink":"https://images.olx.com.pk/thumbnails/228684367-240x180.jpeg"},{"imageLink":"https://images.olx.com.pk/thumbnails/228684183-240x180.jpeg"},{"imageLink":"https://images.olx.com.pk/thumbnails/228684172-240x180.jpeg"},{"imageLink":"https://images.olx.com.pk/thumbnails/228684090-240x180.jpeg"},{"imageLink":"https://images.olx.com.pk/thumbnails/228684036-240x180.jpeg"},{"imageLink":"https://images.olx.com.pk/thumbnails/228684000-240x180.jpeg"},{"imageLink":"https://images.olx.com.pk/thumbnails/228683970-240x180.jpeg"},{"imageLink":"https://images.olx.com.pk/thumbnails/207603415-240x180.jpeg"},{"imageLink":"https://images.olx.com.pk/thumbnails/228683890-240x180.jpeg"},{"imageLink":"https://images.olx.com.pk/thumbnails/228683838-240x180.jpeg"},{"imageLink":"https://images.olx.com.pk/thumbnails/226468285-240x180.jpeg"},{"imageLink":"https://images.olx.com.pk/thumbnails/205506691-240x180.jpeg"},{"imageLink":"https://images.olx.com.pk/thumbnails/211675653-240x180.jpeg"},{"imageLink":"https://images.olx.com.pk/thumbnails/227379308-240x180.jpeg"},{"imageLink":"https://images.olx.com.pk/thumbnails/227936775-240x180.jpeg"},{"imageLink":"https://images.olx.com.pk/thumbnails/227340802-240x180.jpeg"},{"imageLink":"https://images.olx.com.pk/thumbnails/228683890-240x180.jpeg"},{"imageLink":"https://images.olx.com.pk/thumbnails/228683838-240x180.jpeg"},{"imageLink":"https://images.olx.com.pk/thumbnails/228683771-240x180.jpeg"},{"imageLink":"https://images.olx.com.pk/thumbnails/228683611-240x180.jpeg"},{"imageLink":"https://images.olx.com.pk/thumbnails/228683601-240x180.jpeg"},{"imageLink":"https://images.olx.com.pk/thumbnails/228683578-240x180.jpeg"},{"imageLink":"https://images.olx.com.pk/thumbnails/228683537-240x180.jpeg"},{"imageLink":"https://images.olx.com.pk/thumbnails/228683460-240x180.jpeg"},{"imageLink":"https://images.olx.com.pk/thumbnails/228683126-240x180.jpeg"},{"imageLink":"https://images.olx.com.pk/thumbnails/228682641-240x180.jpeg"},{"imageLink":"https://images.olx.com.pk/thumbnails/228669360-240x180.jpeg"},{"imageLink":"https://images.olx.com.pk/thumbnails/228654957-240x180.jpeg"},{"imageLink":"https://images.olx.com.pk/thumbnails/228536257-240x180.jpeg"},{"imageLink":"https://images.olx.com.pk/thumbnails/228390255-240x180.jpeg"},{"imageLink":"https://images.olx.com.pk/thumbnails/225846305-240x180.jpeg"},{"imageLink":"https://images.olx.com.pk/thumbnails/227772995-240x180.jpeg"},{"imageLink":"https://images.olx.com.pk/thumbnails/227365196-240x180.jpeg"},{"imageLink":"https://images.olx.com.pk/thumbnails/226758525-240x180.jpeg"},{"imageLink":"https://images.olx.com.pk/thumbnails/225154486-240x180.jpeg"},{"imageLink":"https://images.olx.com.pk/thumbnails/208265351-240x180.jpeg"},{"imageLink":"https://images.olx.com.pk/thumbnails/228536257-240x180.jpeg"},{"imageLink":"https://images.olx.com.pk/thumbnails/228390255-240x180.jpeg"},{"imageLink":"https://images.olx.com.pk/thumbnails/228387683-240x180.jpeg"},{"imageLink":"https://images.olx.com.pk/thumbnails/227328478-240x180.jpeg"},{"imageLink":"https://images.olx.com.pk/thumbnails/227328139-240x180.jpeg"},{"imageLink":"https://images.olx.com.pk/thumbnails/227327374-240x180.jpeg"},{"imageLink":"https://images.olx.com.pk/thumbnails/226809827-240x180.jpeg"},{"imageLink":"https://images.olx.com.pk/thumbnails/226329566-240x180.jpeg"},{"imageLink":"https://images.olx.com.pk/thumbnails/225630101-240x180.jpeg"},{"imageLink":"https://images.olx.com.pk/thumbnails/228683247-240x180.jpeg"},{"imageLink":"https://images.olx.com.pk/thumbnails/228683238-240x180.jpeg"},{"imageLink":"https://images.olx.com.pk/thumbnails/228683211-240x180.jpeg"},{"imageLink":"https://images.olx.com.pk/thumbnails/228683185-240x180.jpeg"},{"imageLink":"https://images.olx.com.pk/thumbnails/228683143-240x180.jpeg"},{"imageLink":"https://images.olx.com.pk/thumbnails/227894081-240x180.jpeg"},{"imageLink":"https://images.olx.com.pk/thumbnails/227080762-240x180.jpeg"},{"imageLink":"https://images.olx.com.pk/thumbnails/228405392-240x180.jpeg"},{"imageLink":"https://images.olx.com.pk/thumbnails/226786411-240x180.jpeg"},{"imageLink":"https://images.olx.com.pk/thumbnails/227936775-240x180.jpeg"},{"imageLink":"https://images.olx.com.pk/thumbnails/228128549-240x180.jpeg"},{"imageLink":"https://images.olx.com.pk/thumbnails/228683143-240x180.jpeg"},{"imageLink":"https://images.olx.com.pk/thumbnails/228683137-240x180.jpeg"},{"imageLink":"https://images.olx.com.pk/thumbnails/228683054-240x180.jpeg"},{"imageLink":"https://images.olx.com.pk/thumbnails/228683001-240x180.jpeg"},{"imageLink":"https://images.olx.com.pk/thumbnails/228682947-240x180.jpeg"},{"imageLink":"https://images.olx.com.pk/thumbnails/228682936-240x180.jpeg"},{"imageLink":"https://images.olx.com.pk/thumbnails/228682839-240x180.jpeg"},{"imageLink":"https://images.olx.com.pk/thumbnails/228682813-240x180.jpeg"},{"imageLink":"https://images.olx.com.pk/thumbnails/228682782-240x180.jpeg"},{"imageLink":"https://images.olx.com.pk/thumbnails/228682742-240x180.jpeg"},{"imageLink":"https://images.olx.com.pk/thumbnails/224956335-240x180.jpeg"},{"imageLink":"https://images.olx.com.pk/thumbnails/228682663-240x180.jpeg"},{"imageLink":"https://images.olx.com.pk/thumbnails/228682651-240x180.jpeg"},{"imageLink":"https://images.olx.com.pk/thumbnails/228682563-240x180.jpeg"},{"imageLink":"https://images.olx.com.pk/thumbnails/228524751-240x180.jpeg"},{"imageLink":"https://images.olx.com.pk/thumbnails/222775125-240x180.jpeg"},{"imageLink":"https://images.olx.com.pk/thumbnails/189285259-240x180.jpeg"},{"imageLink":"https://images.olx.com.pk/thumbnails/226577729-240x180.jpeg"},{"imageLink":"https://images.olx.com.pk/thumbnails/224813699-240x180.jpeg"},{"imageLink":"https://images.olx.com.pk/thumbnails/217570439-240x180.jpeg"},{"imageLink":"https://images.olx.com.pk/thumbnails/228682563-240x180.jpeg"},{"imageLink":"https://images.olx.com.pk/thumbnails/228682542-240x180.jpeg"},{"imageLink":"https://images.olx.com.pk/thumbnails/228682517-240x180.jpeg"},{"imageLink":"https://images.olx.com.pk/thumbnails/228682262-240x180.jpeg"},{"imageLink":"https://images.olx.com.pk/thumbnails/228682218-240x180.jpeg"},{"imageLink":"https://images.olx.com.pk/thumbnails/228682209-240x180.jpeg"},{"imageLink":"https://images.olx.com.pk/thumbnails/228682180-240x180.jpeg"},{"imageLink":"https://images.olx.com.pk/thumbnails/228682051-240x180.jpeg"},{"imageLink":"https://images.olx.com.pk/thumbnails/228682047-240x180.jpeg"},{"imageLink":"https://images.olx.com.pk/thumbnails/228356980-240x180.jpeg"},{"imageLink":"https://images.olx.com.pk/thumbnails/228681988-240x180.jpeg"},{"imageLink":"https://images.olx.com.pk/thumbnails/228681920-240x180.jpeg"},{"imageLink":"https://images.olx.com.pk/thumbnails/228681820-240x180.jpeg"},{"imageLink":"https://images.olx.com.pk/thumbnails/228681489-240x180.jpeg"},{"imageLink":"https://images.olx.com.pk/thumbnails/227936775-240x180.jpeg"},{"imageLink":"https://images.olx.com.pk/thumbnails/228405392-240x180.jpeg"},{"imageLink":"https://images.olx.com.pk/thumbnails/227416272-240x180.jpeg"},{"imageLink":"https://images.olx.com.pk/thumbnails/221779892-240x180.jpeg"},{"imageLink":"https://images.olx.com.pk/thumbnails/225117037-240x180.jpeg"},{"imageLink":"https://images.olx.com.pk/thumbnails/228510918-240x180.jpeg"},{"imageLink":"https://images.olx.com.pk/thumbnails/228681412-240x180.jpeg"},{"imageLink":"https://images.olx.com.pk/thumbnails/228681368-240x180.jpeg"},{"imageLink":"https://images.olx.com.pk/thumbnails/228681345-240x180.jpeg"},{"imageLink":"https://images.olx.com.pk/thumbnails/228681263-240x180.jpeg"},{"imageLink":"https://images.olx.com.pk/thumbnails/228681268-240x180.jpeg"},{"imageLink":"https://images.olx.com.pk/thumbnails/228681205-240x180.jpeg"},{"imageLink":"https://images.olx.com.pk/thumbnails/228681188-240x180.jpeg"},{"imageLink":"https://images.olx.com.pk/thumbnails/228681183-240x180.jpeg"},{"imageLink":"https://images.olx.com.pk/thumbnails/228681154-240x180.jpeg"},{"imageLink":"https://images.olx.com.pk/thumbnails/228681074-240x180.jpeg"},{"imageLink":"https://images.olx.com.pk/thumbnails/228680892-240x180.jpeg"},{"imageLink":"https://images.olx.com.pk/thumbnails/228680875-240x180.jpeg"},{"imageLink":"https://images.olx.com.pk/thumbnails/228680869-240x180.jpeg"},{"imageLink":"https://images.olx.com.pk/thumbnails/228680810-240x180.jpeg"},{"imageLink":"https://images.olx.com.pk/thumbnails/225485391-240x180.jpeg"},{"imageLink":"https://images.olx.com.pk/thumbnails/228322416-240x180.jpeg"},{"imageLink":"https://images.olx.com.pk/thumbnails/228219477-240x180.jpeg"},{"imageLink":"https://images.olx.com.pk/thumbnails/226203974-240x180.jpeg"},{"imageLink":"https://images.olx.com.pk/thumbnails/212424667-240x180.jpeg"},{"imageLink":"https://images.olx.com.pk/thumbnails/223707817-240x180.jpeg"},{"imageLink":"https://images.olx.com.pk/thumbnails/228680892-240x180.jpeg"},{"imageLink":"https://images.olx.com.pk/thumbnails/228680875-240x180.jpeg"},{"imageLink":"https://images.olx.com.pk/thumbnails/228680869-240x180.jpeg"},{"imageLink":"https://images.olx.com.pk/thumbnails/228680810-240x180.jpeg"},{"imageLink":"https://images.olx.com.pk/thumbnails/224887055-240x180.jpeg"},{"imageLink":"https://images.olx.com.pk/thumbnails/228680882-240x180.jpeg"},{"imageLink":"https://images.olx.com.pk/thumbnails/228680577-240x180.jpeg"},{"imageLink":"https://images.olx.com.pk/thumbnails/228680530-240x180.jpeg"},{"imageLink":"https://images.olx.com.pk/thumbnails/228680399-240x180.jpeg"},{"imageLink":"https://images.olx.com.pk/thumbnails/227279430-240x180.jpeg"},{"imageLink":"https://images.olx.com.pk/thumbnails/228680104-240x180.jpeg"},{"imageLink":"https://images.olx.com.pk/thumbnails/228679999-240x180.jpeg"},{"imageLink":"https://images.olx.com.pk/thumbnails/228679980-240x180.jpeg"},{"imageLink":"https://images.olx.com.pk/thumbnails/228679894-240x180.jpeg"},{"imageLink":"https://images.olx.com.pk/thumbnails/228137641-240x180.jpeg"},{"imageLink":"https://images.olx.com.pk/thumbnails/226892395-240x180.jpeg"},{"imageLink":"https://images.olx.com.pk/thumbnails/225396292-240x180.jpeg"},{"imageLink":"https://images.olx.com.pk/thumbnails/227750903-240x180.jpeg"},{"imageLink":"https://images.olx.com.pk/thumbnails/228283037-240x180.jpeg"},{"imageLink":"https://images.olx.com.pk/thumbnails/227763367-240x180.jpeg"},{"imageLink":"https://images.olx.com.pk/thumbnails/228679980-240x180.jpeg"},{"imageLink":"https://images.olx.com.pk/thumbnails/228679894-240x180.jpeg"},{"imageLink":"https://images.olx.com.pk/thumbnails/228679888-240x180.jpeg"},{"imageLink":"https://images.olx.com.pk/thumbnails/228679861-240x180.jpeg"},{"imageLink":"https://images.olx.com.pk/thumbnails/228679801-240x180.jpeg"},{"imageLink":"https://images.olx.com.pk/thumbnails/228679699-240x180.jpeg"},{"imageLink":"https://images.olx.com.pk/thumbnails/228679569-240x180.jpeg"},{"imageLink":"https://images.olx.com.pk/thumbnails/226245798-240x180.jpeg"},{"imageLink":"https://images.olx.com.pk/thumbnails/220242897-240x180.jpeg"},{"imageLink":"https://images.olx.com.pk/thumbnails/228679373-240x180.jpeg"},{"imageLink":"https://images.olx.com.pk/thumbnails/228679241-240x180.jpeg"},{"imageLink":"https://images.olx.com.pk/thumbnails/228679226-240x180.jpeg"},{"imageLink":"https://images.olx.com.pk/thumbnails/228679207-240x180.jpeg"},{"imageLink":"https://images.olx.com.pk/thumbnails/228679176-240x180.jpeg"}]